{"properties":{"localizedStrings":{"buttonText":"Search","inputTitle":"Enter your search term","placeholderText":"Search the web","placeholderTextMSNntp":"Search Microsoft Start and the web","placeholderTextMSNntpv2":"Search the web and Microsoft Start","tenantAvailableEnterprisePlaceholderText":"Search {0} and the web","tenantMissingEnterprisePlaceholderText":"Search work and the web","voiceButtonTitle":"Search by voice","clearButtonTitle":"Clear","imageButtonTitle":"Search by image","codexBingTitle":"Open Copilot","codexBingASDescription":"Copilot, your everyday AI companion.","codexBingASLinkTitle":"Get started","bingIconText":"Search by Bing","trendingSearchHintText":"Trending"}}}